messagio/__init__.py
messagio/abstract_message_center.py
messagio/autodiscover.py
messagio/const.py
messagio/decorators.py
messagio/exceptions.py
messagio/message_center.py
messagio/tasks.py
messagio-0.7.dist-info/LICENSE
messagio-0.7.dist-info/METADATA
messagio-0.7.dist-info/WHEEL
messagio-0.7.dist-info/top_level.txt
messagio-0.7.dist-info/RECORD
