Metadata-Version: 2.1
Name: messagio
Version: 0.7
Summary: Define events (aka messagios) and then listen for those events, like pubsub, but better. Uses celery for transport.
Home-page: https://github.com/zeraien/messagio
Author: Dimo Fedortchenko
Author-email: d@onedaybeard.net
License: UNKNOWN
Project-URL: Bug Tracker, https://github.com/zeraien/messagio/issues
Platform: UNKNOWN
Classifier: Development Status :: 3 - Alpha
Classifier: Intended Audience :: Developers
Classifier: License :: OSI Approved :: MIT License
Classifier: Framework :: Celery
Classifier: Framework :: Django
Classifier: Topic :: Software Development :: Libraries
Classifier: Programming Language :: Python :: 3
Requires-Python: >=3.7
License-File: LICENSE
